xrayweb/__init__.py
xrayweb/version.py
xrayweb/webapp.py
xrayweb/static/gse_logo.ico
xrayweb/static/ixas_logo.ico
xrayweb/static/plotly-2021.js
xrayweb/static/style.css
xrayweb/templates/about.html
xrayweb/templates/analyzers.html
xrayweb/templates/attenuation.html
xrayweb/templates/darwinwidth.html
xrayweb/templates/elements.html
xrayweb/templates/formulas.html
xrayweb/templates/ionchamber.html
xrayweb/templates/layout.html
xrayweb/templates/materials.html
xrayweb/templates/periodic_table.html
xrayweb/templates/reflectivity.html
xrayweb/templates/scattering.html
xrayweb/templates/transmission_sample.html
xrayweb-2024.11.0.dist-info/LICENSE
xrayweb-2024.11.0.dist-info/METADATA
xrayweb-2024.11.0.dist-info/WHEEL
xrayweb-2024.11.0.dist-info/top_level.txt
xrayweb-2024.11.0.dist-info/RECORD
