Metadata-Version: 2.1
Name: xrayweb
Version: 2024.11.0
Summary: Web interface for X-ray Properties of the elements
Author: Alex Nicolellis
Author-email: Matthew Newville <newville@cars.uchicago.edu>
License: MIT License
Project-URL: Homepage,  https://github.com/xraypy/xrayweb
Project-URL: Documentation, https://github.com/xraypy/xrayweb
Project-URL: Tracker, https://github.com/xraypy/xrayweb/issues
Keywords: X-ray spectroscopy,Physics
Classifier: Development Status :: 5 - Production/Stable
Classifier: Intended Audience :: Developers
Classifier: License :: OSI Approved :: MIT License
Classifier: Operating System :: OS Independent
Classifier: Programming Language :: Python :: 3.9
Classifier: Programming Language :: Python :: 3.10
Classifier: Programming Language :: Python :: 3.11
Classifier: Programming Language :: Python :: 3.12
Classifier: Programming Language :: Python :: 3.13
Requires-Python: >=3.9
License-File: LICENSE
Requires-Dist: xraydb
Requires-Dist: sqlalchemy >=2
Requires-Dist: numpy
Requires-Dist: flask
Requires-Dist: plotly
Provides-Extra: all
Requires-Dist: xrayweb[dev] ; extra == 'all'
Provides-Extra: dev
Requires-Dist: build ; extra == 'dev'
Requires-Dist: twine ; extra == 'dev'
